pvleoparddemo/LICENSE
pvleoparddemo/leopard_demo_file.py
pvleoparddemo/leopard_demo_mic.py
pvleoparddemo-3.0.0.dist-info/METADATA
pvleoparddemo-3.0.0.dist-info/WHEEL
pvleoparddemo-3.0.0.dist-info/entry_points.txt
pvleoparddemo-3.0.0.dist-info/top_level.txt
pvleoparddemo-3.0.0.dist-info/RECORD
