Metadata-Version: 2.1
Name: pvleoparddemo
Version: 3.0.0
Summary: Leopard speech-to-text engine demos
Home-page: https://github.com/Picovoice/leopard
Author: Picovoice
Author-email: hello@picovoice.ai
Keywords: Speech-to-Text,ASR,Speech Recognition,Voice Recognition,Automatic Speech Recognition
Classifier: Development Status :: 5 - Production/Stable
Classifier: Intended Audience :: Developers
Classifier: License :: OSI Approved :: Apache Software License
Classifier: Operating System :: OS Independent
Classifier: Programming Language :: Python :: 3
Classifier: Topic :: Multimedia :: Sound/Audio :: Speech
Requires-Python: >=3.9
Requires-Dist: pvleopard (==3.0.0)
Requires-Dist: pvrecorder (==1.2.4)
Requires-Dist: tabulate (==0.8.10)
